ANSI_Color-1.0.1.dist-info/DESCRIPTION.rst
ANSI_Color-1.0.1.dist-info/METADATA
ANSI_Color-1.0.1.dist-info/metadata.json
ANSI_Color-1.0.1.dist-info/RECORD
ANSI_Color-1.0.1.dist-info/top_level.txt
ANSI_Color-1.0.1.dist-info/WHEEL
ANSI_Color-1.0.1.dist-info/zip-safe
ansicolor/__init__.py
ansicolor/termcolor.py
