Metadata-Version: 2.0
Name: ANSI-Color
Version: 1.0.1
Summary: print colorful on your *sh
Home-page: https://github.com/bunnyswe/PythonAnsiColor
Author: Naitiz
Author-email: bunnyswe@qq.com
License: The MIT License
Keywords: asni color term shell
Platform: UNKNOWN
